novelwriter/__init__.py
novelwriter/common.py
novelwriter/config.py
novelwriter/constants.py
novelwriter/enum.py
novelwriter/error.py
novelwriter/guimain.py
novelwriter/shared.py
novelwriter/splash.py
novelwriter/types.py
novelwriter/assets/manual.pdf
novelwriter/assets/manual_fr.pdf
novelwriter/assets/sample.zip
novelwriter/assets/i18n/nw_cs_CZ.qm
novelwriter/assets/i18n/nw_de_DE.qm
novelwriter/assets/i18n/nw_en_US.qm
novelwriter/assets/i18n/nw_es_419.qm
novelwriter/assets/i18n/nw_fr_FR.qm
novelwriter/assets/i18n/nw_it_IT.qm
novelwriter/assets/i18n/nw_ja_JP.qm
novelwriter/assets/i18n/nw_nb_NO.qm
novelwriter/assets/i18n/nw_nl_NL.qm
novelwriter/assets/i18n/nw_pl_PL.qm
novelwriter/assets/i18n/nw_pt_BR.qm
novelwriter/assets/i18n/nw_ru_RU.qm
novelwriter/assets/i18n/nw_zh_CN.qm
novelwriter/assets/i18n/project_cs_CZ.json
novelwriter/assets/i18n/project_de_DE.json
novelwriter/assets/i18n/project_en_GB.json
novelwriter/assets/i18n/project_en_US.json
novelwriter/assets/i18n/project_es_419.json
novelwriter/assets/i18n/project_fr_FR.json
novelwriter/assets/i18n/project_it_IT.json
novelwriter/assets/i18n/project_ja_JP.json
novelwriter/assets/i18n/project_nb_NO.json
novelwriter/assets/i18n/project_nl_NL.json
novelwriter/assets/i18n/project_nn_NO.json
novelwriter/assets/i18n/project_pl_PL.json
novelwriter/assets/i18n/project_pt_BR.json
novelwriter/assets/i18n/project_ru_RU.json
novelwriter/assets/i18n/project_zh_CN.json
novelwriter/assets/icons/font_awesome.icons
novelwriter/assets/icons/material_filled_normal.icons
novelwriter/assets/icons/material_filled_thin.icons
novelwriter/assets/icons/material_rounded_normal.icons
novelwriter/assets/icons/material_rounded_thin.icons
novelwriter/assets/icons/material_sharp_normal.icons
novelwriter/assets/icons/material_sharp_thin.icons
novelwriter/assets/icons/none.svg
novelwriter/assets/icons/novelwriter.ico
novelwriter/assets/icons/novelwriter.svg
novelwriter/assets/icons/remix_filled.icons
novelwriter/assets/icons/remix_outline.icons
novelwriter-2.8.2.dist-info/licenses/LICENSE.md
novelwriter-2.8.2.dist-info/licenses/setup/LICENSE-Apache-2.0.txt
novelwriter-2.8.2.dist-info/METADATA
novelwriter-2.8.2.dist-info/WHEEL
novelwriter-2.8.2.dist-info/entry_points.txt
novelwriter-2.8.2.dist-info/top_level.txt
novelwriter-2.8.2.dist-info/RECORD
