Metadata-Version: 2.4
Name: novelWriter
Version: 2.8.2
Summary: A plain text editor for planning and writing novels
Author-email: Veronica Berglyd Olsen <code@vkbo.net>
License-Expression: GPL-3.0-or-later AND Apache-2.0 AND CC-BY-4.0
Project-URL: Homepage, https://novelwriter.io
Project-URL: Documentation, https://docs.novelwriter.io
Project-URL: Repository, https://github.com/vkbo/novelWriter
Project-URL: Issues, https://github.com/vkbo/novelWriter/issues
Classifier: Programming Language :: Python :: 3 :: Only
Classifier: Programming Language :: Python :: 3.11
Classifier: Programming Language :: Python :: 3.12
Classifier: Programming Language :: Python :: 3.13
Classifier: Programming Language :: Python :: 3.14
Classifier: Programming Language :: Python :: Implementation :: CPython
Classifier: Development Status :: 5 - Production/Stable
Classifier: Operating System :: OS Independent
Classifier: Intended Audience :: End Users/Desktop
Classifier: Natural Language :: English
Classifier: Topic :: Text Editors
Requires-Python: >=3.11
License-File: LICENSE.md
License-File: setup/LICENSE-Apache-2.0.txt
Requires-Dist: pyqt6>=6.4
Requires-Dist: pyenchant>=3.3.0
Dynamic: license-file
